ZohoSDPlusAPI/__init__.py
ZohoSDPlusAPI/admin.py
ZohoSDPlusAPI/announcements.py
ZohoSDPlusAPI/approvals.py
ZohoSDPlusAPI/asset.py
ZohoSDPlusAPI/change.py
ZohoSDPlusAPI/cmdb.py
ZohoSDPlusAPI/comments.py
ZohoSDPlusAPI/contract.py
ZohoSDPlusAPI/device_registration.py
ZohoSDPlusAPI/personalization.py
ZohoSDPlusAPI/problem.py
ZohoSDPlusAPI/project.py
ZohoSDPlusAPI/purchase_order.py
ZohoSDPlusAPI/release.py
ZohoSDPlusAPI/report.py
ZohoSDPlusAPI/request.py
ZohoSDPlusAPI/sdp_api_core.py
ZohoSDPlusAPI/solutions.py
ZohoSDPlusAPI/space.py
ZohoSDPlusAPI/task.py
ZohoSDPlusAPI/worklog.py
ZohoSDPlusAPI-0.1.6.dist-info/METADATA
ZohoSDPlusAPI-0.1.6.dist-info/WHEEL
ZohoSDPlusAPI-0.1.6.dist-info/top_level.txt
ZohoSDPlusAPI-0.1.6.dist-info/RECORD
