Metadata-Version: 2.1
Name: ZohoSDPlusAPI
Version: 0.1.6
Summary: Этот модуль умеет работать с REST API Zoho SD Plus Manageengine через requests
Home-page: https://github.com/azatkhafizov/zoho_sdp_api
Author: AzatXafizov
Author-email: hafizov.azat.m@gmail.com
Project-URL: GitHub, https://github.com/azatkhafizov/zoho_sdp_api
Keywords: Zoho zoho rest REST api API requests
Classifier: Programming Language :: Python :: 3.11
Classifier: License :: OSI Approved :: MIT License
Classifier: Operating System :: OS Independent
Requires-Python: >=3.6
Requires-Dist: requests ==2.31.0
Requires-Dist: requests-toolbelt ==1.0.0
